trello_cli/__init__.py
trello_cli/database.py
trello_cli/main.py
trello_cli/models.py
trello_cli/trello.py
trello_tools-0.2.0.dist-info/METADATA
trello_tools-0.2.0.dist-info/WHEEL
trello_tools-0.2.0.dist-info/entry_points.txt
trello_tools-0.2.0.dist-info/licenses/LICENSE
trello_tools-0.2.0.dist-info/RECORD
