Metadata-Version: 2.4
Name: trello-tools
Version: 0.2.0
Summary: A CLI for interacting with Trello.
Project-URL: Homepage, https://github.com/jhaisley/trello-tools
Project-URL: Repository, https://github.com/jhaisley/trello-tools
Project-URL: Issues, https://github.com/jhaisley/trello-tools/issues
Author-email: Jordan Haisley <jordanhaisley@google.com>
License: MIT
License-File: LICENSE
Keywords: cli,productivity,project-management,trello
Classifier: Development Status :: 4 - Beta
Classifier: Environment :: Console
Classifier: Intended Audience :: Developers
Classifier: Intended Audience :: End Users/Desktop
Classifier: License :: OSI Approved :: MIT License
Classifier: Operating System :: OS Independent
Classifier: Programming Language :: Python :: 3
Classifier: Programming Language :: Python :: 3.11
Classifier: Programming Language :: Python :: 3.12
Classifier: Programming Language :: Python :: 3.13
Classifier: Topic :: Office/Business
Classifier: Topic :: Utilities
Requires-Python: >=3.11
Requires-Dist: alembic
Requires-Dist: google-generativeai
Requires-Dist: py-trello
Requires-Dist: rich
Requires-Dist: sqlalchemy
Requires-Dist: typer
Provides-Extra: dev
Requires-Dist: bandit>=1.8.6; extra == 'dev'
Requires-Dist: bump2version>=1.0.1; extra == 'dev'
Requires-Dist: detect-secrets>=1.5.0; extra == 'dev'
Requires-Dist: pytest>=8.4.1; extra == 'dev'
Requires-Dist: ruff>=0.12.3; extra == 'dev'
